<?xml version="1.0" encoding="UTF-8"?>
<!--This file was created by G+Smo 21.12.0-->
<xml>
 <Matrix rows="5" cols="7" id="0">0.25 129 0.05516393337244858 1.23595808427082 37.0707936045302 2.138416553765221e-15 3.424570344324062e-4937 
0.125 465 0.001944718972963055 0.08722055905918243 6.973901259391843 2.021650219739057e-15 nan 
0.0625 1713 9.055054632457752e-05 0.00847831206773474 1.515280680286102 3.359403386579887e-15 -nan 
0.03125 6513 5.0172386469589e-06 0.0009765801181401982 0.3559888277905306 3.822722554512786e-15 nan 
0.015625 25329 3.005311608934719e-07 0.0001190086899249063 0.086641870865679 9.932200225988659e-15 1.029920225642574e-4934 
</Matrix>
 <string label="Label" id="1">Meshsize, dofs, l2err, h1err, h2err, iFaceErr, cond_num, (penalty)</string>
 <string label="Degree" id="2">3</string>
 <string label="Regularity" id="3">2</string>
 <string label="NumRefine" id="4">4</string>
 <string label="Method" id="5">0</string>
</xml>

