<?xml version="1.0" encoding="UTF-8"?>
<!--This file was created by G+Smo 21.12.0-->
<xml>
 <Matrix rows="5" cols="8" id="0">0.25 78 0.5660041298048567 8.360401903320973 138.347815694607 1.321354691640484 -nan 0.042 
0.125 210 0.04700013392773646 1.148134544574988 35.01835590544844 1.387934184091883 -nan 0.08400000000000001 
0.0625 666 0.0003812727317278978 0.0249458128043088 2.211552533290276 0.04062559494345764 nan 0.168 
0.03125 2346 5.995801315425999e-06 0.0009957860972281527 0.1966046954184536 0.001327576456619437 nan 0.336 
0.015625 8778 1.545879239303948e-07 5.498969915644965e-05 0.02233921762220939 6.731488302532161e-05 0 0.672 
</Matrix>
 <string label="Label" id="1">Meshsize, dofs, l2err, h1err, h2err, iFaceErr, cond_num, (penalty)</string>
 <string label="Degree" id="2">4</string>
 <string label="Regularity" id="3">3</string>
 <string label="NumRefine" id="4">4</string>
 <string label="Method" id="5">1</string>
</xml>

