<?xml version="1.0" encoding="UTF-8"?>
<!--This file was created by G+Smo 21.12.0-->
<xml>
 <Matrix rows="5" cols="8" id="0">0.25 78 0.6982368720208358 9.223038575643991 145.2446032600238 0.08054873785328738 nan 18617.48 
0.125 210 0.09455682154012464 1.891595799982741 46.46186011909398 0.0556674962597602 nan 37234.96 
0.0625 666 0.009191233573293335 0.2187467105944044 5.966451947425373 0.02898021939118722 nan 74469.92 
0.03125 2346 2.977751382136703e-05 0.001236656812972763 0.1979174244688023 0.001277526646573176 nan 148939.84 
0.015625 8778 2.094946614026437e-07 5.513462902935134e-05 0.0223349007847949 6.400492707626378e-05 0 297879.68 
</Matrix>
 <string label="Label" id="1">Meshsize, dofs, l2err, h1err, h2err, iFaceErr, cond_num, (penalty)</string>
 <string label="Degree" id="2">4</string>
 <string label="Regularity" id="3">3</string>
 <string label="NumRefine" id="4">4</string>
 <string label="Method" id="5">1</string>
</xml>

