<?xml version="1.0" encoding="UTF-8"?>
<!--This file was created by G+Smo 21.12.0-->
<xml>
 <Matrix rows="5" cols="8" id="0">0.25 105 0.232607114236477 4.335113240967042 88.40553426877548 0.8955554937710924 nan 0.0102 
0.125 253 0.03725819950450764 0.9184109826143237 25.81794265414778 0.6623653877708343 -nan 0.0204 
0.0625 741 9.002167310028381e-05 0.006842454004485489 0.6020583840140115 0.01287847621830299 nan 0.0408 
0.03125 2485 6.514465722961836e-07 0.0001150782949257319 0.02275869299026998 0.0001628706736058943 nan 0.08160000000000001 
0.015625 9045 7.829841660779645e-09 2.953291512074402e-06 0.001228158651793256 3.693051666169199e-06 0 0.1632 
</Matrix>
 <string label="Label" id="1">Meshsize, dofs, l2err, h1err, h2err, iFaceErr, cond_num, (penalty)</string>
 <string label="Degree" id="2">5</string>
 <string label="Regularity" id="3">4</string>
 <string label="NumRefine" id="4">4</string>
 <string label="Method" id="5">1</string>
</xml>

