<?xml version="1.0" encoding="UTF-8"?>
<!--This file was created by G+Smo 21.12.0-->
<xml>
 <Matrix rows="5" cols="8" id="0">0.25 105 0.2326070210627151 4.335112464166586 88.4055000814013 0.8954757206560002 -nan 0.00424 
0.125 253 0.03725789467330854 0.9184062437745853 25.81797308735439 0.6623974877464949 nan 0.00848 
0.0625 741 9.002151018042488e-05 0.00684245264928176 0.6020583749145009 0.01287847625608487 nan 0.01696 
0.03125 2485 6.514465685726623e-07 0.0001150782946125833 0.02275869279237716 0.0001628706111060785 -nan 0.03392 
0.015625 9045 7.829841680577971e-09 2.953291512211509e-06 0.001228158648687914 3.693050460699941e-06 0 0.06784 
</Matrix>
 <string label="Label" id="1">Meshsize, dofs, l2err, h1err, h2err, iFaceErr, cond_num, (penalty)</string>
 <string label="Degree" id="2">5</string>
 <string label="Regularity" id="3">4</string>
 <string label="NumRefine" id="4">4</string>
 <string label="Method" id="5">1</string>
</xml>

