<?xml version="1.0" encoding="UTF-8"?>
<!--This file was created by G+Smo 21.12.0-->
<xml>
 <Matrix rows="5" cols="8" id="0">0.25 105 0.3547034035082266 5.050357561239504 96.5444187336105 0.01584192109088984 nan 1608444 
0.125 253 0.09263010832608972 1.757571015446739 41.80117171725722 0.0062711029678311 nan 3216888 
0.0625 741 0.0239180110863164 0.5459382366632637 13.70206401776553 0.004084890369560252 nan 6433776 
0.03125 2485 5.275829042523314e-05 0.001427250059168385 0.04834570551855322 0.0001619642179470081 -nan 12867552 
0.015625 9045 6.792017021471233e-08 3.362271245541912e-06 0.001238572854135943 3.687655772809294e-06 0 25735104 
</Matrix>
 <string label="Label" id="1">Meshsize, dofs, l2err, h1err, h2err, iFaceErr, cond_num, (penalty)</string>
 <string label="Degree" id="2">5</string>
 <string label="Regularity" id="3">4</string>
 <string label="NumRefine" id="4">4</string>
 <string label="Method" id="5">1</string>
</xml>

