<?xml version="1.0" encoding="UTF-8"?>
<!--This file was created by G+Smo 21.12.0-->
<xml>
 <Matrix rows="5" cols="8" id="0">0.25 78 0.5660026865538236 8.360391212581187 138.347394540562 1.320045637753946 nan 0.01308 
0.125 210 0.04699415108353398 1.148066038049829 35.01917600133745 1.388282704789392 -nan 0.02616 
0.0625 666 0.0003812627754224398 0.02494571174536042 2.211548874847846 0.04062425206324421 nan 0.05232 
0.03125 2346 5.995793563198122e-06 0.00099578551735417 0.1966044632377361 0.001327456068424781 nan 0.10464 
0.015625 8778 1.545879145246066e-07 5.498968380623729e-05 0.02233920335681799 6.730674025778901e-05 0 0.20928 
</Matrix>
 <string label="Label" id="1">Meshsize, dofs, l2err, h1err, h2err, iFaceErr, cond_num, (penalty)</string>
 <string label="Degree" id="2">4</string>
 <string label="Regularity" id="3">3</string>
 <string label="NumRefine" id="4">4</string>
 <string label="Method" id="5">1</string>
</xml>

