<?xml version="1.0" encoding="UTF-8"?>
<!--This file was created by G+Smo 21.12.0-->
<xml>
 <Matrix rows="5" cols="8" id="0">0.25 105 0.2582164921418831 4.516367467324978 91.15790368922293 0.07922858884728813 -nan 24923.36 
0.125 253 0.07401992345949094 1.535235457316329 36.26741704120274 0.03711042065025119 -nan 49846.72 
0.0625 741 0.002165664642759082 0.05847631349482329 1.812799015865349 0.01061257385791494 nan 99693.44 
0.03125 2485 1.066159181481946e-06 0.0001177712633034105 0.02278966914839834 0.0001625624943619314 -nan 199386.88 
0.015625 9045 7.895627452844061e-09 2.95428390376775e-06 0.001228385200135005 3.688012787027469e-06 0 398773.76 
</Matrix>
 <string label="Label" id="1">Meshsize, dofs, l2err, h1err, h2err, iFaceErr, cond_num, (penalty)</string>
 <string label="Degree" id="2">5</string>
 <string label="Regularity" id="3">4</string>
 <string label="NumRefine" id="4">4</string>
 <string label="Method" id="5">1</string>
</xml>

