<?xml version="1.0" encoding="UTF-8"?>
<!--This file was created by G+Smo 21.12.0-->
<xml>
 <Matrix rows="5" cols="8" id="0">0.25 105 0.2371187089874978 4.359491463998396 88.8468800167117 0.1797013227419104 nan 2045.156 
0.125 253 0.05615828539918472 1.237387495654287 30.5381588150448 0.1431783571170356 nan 4090.312 
0.0625 741 0.0003012049522699136 0.01061447293563927 0.6511427459458765 0.01244708624058957 nan 8180.624 
0.03125 2485 6.565913669133739e-07 0.0001151157831538142 0.02276000351012324 0.000162590555002015 nan 16361.248 
0.015625 9045 7.830419610903033e-09 2.953339456728321e-06 0.00122817275471416 3.688408791371935e-06 0 32722.496 
</Matrix>
 <string label="Label" id="1">Meshsize, dofs, l2err, h1err, h2err, iFaceErr, cond_num, (penalty)</string>
 <string label="Degree" id="2">5</string>
 <string label="Regularity" id="3">4</string>
 <string label="NumRefine" id="4">4</string>
 <string label="Method" id="5">1</string>
</xml>

