<?xml version="1.0" encoding="UTF-8"?>
<!--This file was created by G+Smo 21.12.0-->
<xml>
 <Matrix rows="5" cols="8" id="0">0.25 78 0.5660223669561792 8.360540235988371 138.353342179934 1.338265942459836 nan 0.39868 
0.125 210 0.04707386169358012 1.148983433196278 35.00860033270686 1.38375723279848 nan 0.79736 
0.0625 666 0.0003813957020346029 0.02494706711077722 2.211598956945524 0.04064267183987275 nan 1.59472 
0.03125 2346 5.995897672970976e-06 0.0009957934228354338 0.1966076360488436 0.001329101308006799 nan 3.18944 
0.015625 8778 1.545883275448898e-07 5.49898935953681e-05 0.02233939818491594 6.741792736856814e-05 0 6.37888 
</Matrix>
 <string label="Label" id="1">Meshsize, dofs, l2err, h1err, h2err, iFaceErr, cond_num, (penalty)</string>
 <string label="Degree" id="2">4</string>
 <string label="Regularity" id="3">3</string>
 <string label="NumRefine" id="4">4</string>
 <string label="Method" id="5">1</string>
</xml>

