<?xml version="1.0" encoding="UTF-8"?>
<!--This file was created by G+Smo 21.12.0-->
<xml>
 <Matrix rows="5" cols="8" id="0">0.25 78 0.660842993847963 8.961611862640053 142.5975036582661 0.2508471755209341 nan 3983.772 
0.125 210 0.08638066636709503 1.791072850759833 44.28533231747244 0.1079700201349255 nan 7967.544 
0.0625 666 0.002944089891814286 0.07607974705068876 2.897837667068902 0.03557644403613251 nan 15935.088 
0.03125 2346 9.095610167223215e-06 0.001011636549058439 0.1966310555050194 0.001278855732449738 nan 31870.176 
0.015625 8778 1.588422836482709e-07 5.499266427178209e-05 0.02233359196908086 6.400696106185011e-05 0 63740.352 
</Matrix>
 <string label="Label" id="1">Meshsize, dofs, l2err, h1err, h2err, iFaceErr, cond_num, (penalty)</string>
 <string label="Degree" id="2">4</string>
 <string label="Regularity" id="3">3</string>
 <string label="NumRefine" id="4">4</string>
 <string label="Method" id="5">1</string>
</xml>

