<?xml version="1.0" encoding="UTF-8"?>
<!--This file was created by G+Smo 21.12.0-->
<xml>
 <Matrix rows="5" cols="8" id="0">0.25 105 0.2326326944091545 4.335347395575388 88.41653048112627 0.920374103716062 nan 1.64424 
0.125 253 0.03734101890506025 0.919704102288634 25.81059505062245 0.6537866120447358 -nan 3.28848 
0.0625 741 9.006666875245005e-05 0.006842830154967855 0.6020611113156284 0.01287850791548686 nan 6.57696 
0.03125 2485 6.514476448026643e-07 0.0001150783891376421 0.02275875135307287 0.0001628892327904207 nan 13.15392 
0.015625 9045 7.829840159367373e-09 2.953291503009482e-06 0.001228159564154555 3.693406859976636e-06 0 26.30784 
</Matrix>
 <string label="Label" id="1">Meshsize, dofs, l2err, h1err, h2err, iFaceErr, cond_num, (penalty)</string>
 <string label="Degree" id="2">5</string>
 <string label="Regularity" id="3">4</string>
 <string label="NumRefine" id="4">4</string>
 <string label="Method" id="5">1</string>
</xml>

