<?xml version="1.0" encoding="UTF-8"?>
<!--This file was created by G+Smo 21.12.0-->
<xml>
 <Matrix rows="5" cols="8" id="0">0.25 78 0.5766591988624209 8.790526380160188 189.0286279706594 17.25795104655274 nan 9.46424 
0.125 210 0.04902803940226108 1.175958392838464 35.30388579089869 1.525337073014103 nan 18.92848 
0.0625 666 0.0003846668643395295 0.02498953103012215 2.214866126670546 0.04191314212337369 nan 37.85696 
0.03125 2346 5.999314413791604e-06 0.0009962348651474696 0.1967964914356991 0.001426381246358513 nan 75.71392 
0.015625 8778 1.546103430800297e-07 5.500181909609224e-05 0.02235061064454419 7.369133759579755e-05 0 151.42784 
</Matrix>
 <string label="Label" id="1">Meshsize, dofs, l2err, h1err, h2err, iFaceErr, cond_num, (penalty)</string>
 <string label="Degree" id="2">4</string>
 <string label="Regularity" id="3">3</string>
 <string label="NumRefine" id="4">4</string>
 <string label="Method" id="5">1</string>
</xml>

