<?xml version="1.0" encoding="UTF-8"?>
<!--This file was created by G+Smo 21.12.0-->
<xml>
 <Matrix rows="5" cols="8" id="0">0.25 105 0.1572968379501716 3.140397928588417 66.97740381318203 0.2448792739440569 nan 0.35184 
0.125 253 0.00702909441301231 0.2275715917086597 8.393634386203796 0.09402477664427243 nan 0.70368 
0.0625 741 2.449766895732263e-05 0.002125151423063079 0.1888115093060613 0.0004611108172825472 nan 1.40736 
0.03125 2485 2.252766319636215e-07 4.243155933731336e-05 0.008125289755216958 3.698679980772821e-06 -nan 2.81472 
0.015625 9045 2.930674850463349e-09 1.149250989893625e-06 0.0004553038672769296 4.587350200983028e-08 0 5.62944 
</Matrix>
 <string label="Label" id="1">Meshsize, dofs, l2err, h1err, h2err, iFaceErr, cond_num, (penalty)</string>
 <string label="Degree" id="2">5</string>
 <string label="Regularity" id="3">4</string>
 <string label="NumRefine" id="4">4</string>
 <string label="Method" id="5">1</string>
</xml>

