<?xml version="1.0" encoding="UTF-8"?>
<!--This file was created by G+Smo 21.12.0-->
<xml>
 <Matrix rows="5" cols="8" id="0">0.25 78 0.3428030908508798 6.062191275265405 114.0427243818344 0.4816915008323511 -nan 2.49432 
0.125 210 0.01531723237628293 0.4576113725168777 16.2250479766572 0.1578593485939594 -nan 4.98864 
0.0625 666 0.0001269084839718838 0.01075916333958805 0.9730574325471622 0.001770411251791525 nan 9.97728 
0.03125 2346 2.534307113224014e-06 0.0004854731875749628 0.09517911193405498 4.524433121644679e-05 nan 19.95456 
0.015625 8778 6.931853008327329e-08 2.762761551661485e-05 0.0111301349414644 2.24311218848246e-06 -nan 39.90912 
</Matrix>
 <string label="Label" id="1">Meshsize, dofs, l2err, h1err, h2err, iFaceErr, cond_num, (penalty)</string>
 <string label="Degree" id="2">4</string>
 <string label="Regularity" id="3">3</string>
 <string label="NumRefine" id="4">4</string>
 <string label="Method" id="5">1</string>
</xml>

