<?xml version="1.0" encoding="UTF-8"?>
<!--This file was created by G+Smo 21.12.0-->
<xml>
 <Matrix rows="5" cols="8" id="0">0.25 78 0.342818537229399 6.079671130139154 121.291956531874 5.038646609701938 -nan 37.43856 
0.125 210 0.01586338982253603 0.523776702099731 39.80234870324617 3.316587165748564 -nan 74.87712000000001 
0.0625 666 0.0001269658297442868 0.01076847066305588 0.9814518024337751 0.008264530939299501 nan 149.75424 
0.03125 2346 2.539217123050436e-06 0.0004871711270155831 0.09788373454565227 0.001053977709102378 nan 299.50848 
0.015625 8778 6.935466039780968e-08 2.76499365388798e-05 0.01119568402709551 3.981414981963191e-05 -nan 599.01696 
</Matrix>
 <string label="Label" id="1">Meshsize, dofs, l2err, h1err, h2err, iFaceErr, cond_num, (penalty)</string>
 <string label="Degree" id="2">4</string>
 <string label="Regularity" id="3">3</string>
 <string label="NumRefine" id="4">4</string>
 <string label="Method" id="5">1</string>
</xml>

