<?xml version="1.0" encoding="UTF-8"?>
<!--This file was created by G+Smo 21.12.0-->
<xml>
 <Matrix rows="5" cols="8" id="0">0.25 105 0.1572973970026305 3.14040461990329 66.97741880856014 0.2449187318792691 -nan 0.4518 
0.125 253 0.007029248734161879 0.227573647973977 8.393637056322316 0.09402148630670945 -nan 0.9036 
0.0625 741 2.449767474548744e-05 0.002125151492578463 0.1888115105107361 0.0004611114701447054 nan 1.8072 
0.03125 2485 2.252766325764928e-07 4.243155932923923e-05 0.008125289773693668 3.698732084315456e-06 -nan 3.6144 
0.015625 9045 2.930674756130863e-09 1.149250989278846e-06 0.0004553038676390574 4.587582819294005e-08 0 7.2288 
</Matrix>
 <string label="Label" id="1">Meshsize, dofs, l2err, h1err, h2err, iFaceErr, cond_num, (penalty)</string>
 <string label="Degree" id="2">5</string>
 <string label="Regularity" id="3">4</string>
 <string label="NumRefine" id="4">4</string>
 <string label="Method" id="5">1</string>
</xml>

