<?xml version="1.0" encoding="UTF-8"?>
<!--This file was created by G+Smo 21.12.0-->
<xml>
 <Matrix rows="5" cols="8" id="0">0.25 105 0.1572955646206627 3.140382694045878 66.97737007543626 0.2447912713204323 nan 0.12412 
0.125 253 0.007028742812726596 0.2275669076624289 8.393628307558746 0.09403229461558206 nan 0.24824 
0.0625 741 2.449765577132272e-05 0.002125151264746874 0.1888115065794389 0.00046110936023347 nan 0.49648 
0.03125 2485 2.252766305716559e-07 4.243155935545645e-05 0.008125289713496403 3.69856236250601e-06 -nan 0.99296 
0.015625 9045 2.930674748436738e-09 1.149250990937129e-06 0.0004553038664599274 4.586825033095824e-08 0 1.98592 
</Matrix>
 <string label="Label" id="1">Meshsize, dofs, l2err, h1err, h2err, iFaceErr, cond_num, (penalty)</string>
 <string label="Degree" id="2">5</string>
 <string label="Regularity" id="3">4</string>
 <string label="NumRefine" id="4">4</string>
 <string label="Method" id="5">1</string>
</xml>

