<?xml version="1.0" encoding="UTF-8"?>
<!--This file was created by G+Smo 21.12.0-->
<xml>
 <Matrix rows="5" cols="8" id="0">0.25 78 0.3427803037159476 6.061847731973579 114.0394775716718 0.4577561518659876 -nan 0.008999999999999999 
0.125 210 0.01530814527174415 0.4574958345223527 16.22455917853757 0.1580686710336555 nan 0.018 
0.0625 666 0.000126907384434614 0.0107591441156894 0.9730509921898486 0.001756839270051138 nan 0.036 
0.03125 2346 2.534307189368506e-06 0.0004854728154355045 0.09517866016529537 4.335042478435781e-05 nan 0.07199999999999999 
0.015625 8778 6.931853443829777e-08 2.76276026815842e-05 0.0111301055748511 2.095194626536377e-06 nan 0.144 
</Matrix>
 <string label="Label" id="1">Meshsize, dofs, l2err, h1err, h2err, iFaceErr, cond_num, (penalty)</string>
 <string label="Degree" id="2">4</string>
 <string label="Regularity" id="3">3</string>
 <string label="NumRefine" id="4">4</string>
 <string label="Method" id="5">1</string>
</xml>

