<?xml version="1.0" encoding="UTF-8"?>
<!--This file was created by G+Smo 21.12.0-->
<xml>
 <Matrix rows="5" cols="8" id="0">0.25 78 0.342793999776872 6.062052867130004 114.0413345375968 0.4717027843659272 -nan 1.51276 
0.125 210 0.01531364493759409 0.4575657129448336 16.22485027742763 0.1579373669842116 nan 3.02552 
0.0625 666 0.0001269080495249491 0.01075915547764485 0.9730547093446827 0.001764683792057518 nan 6.05104 
0.03125 2346 2.534307142804695e-06 0.0004854730303347795 0.09517892074584843 4.445297580515197e-05 nan 12.10208 
0.015625 8778 6.931852996166348e-08 2.762761009354922e-05 0.01113012251124522 2.181750457360279e-06 nan 24.20416 
</Matrix>
 <string label="Label" id="1">Meshsize, dofs, l2err, h1err, h2err, iFaceErr, cond_num, (penalty)</string>
 <string label="Degree" id="2">4</string>
 <string label="Regularity" id="3">3</string>
 <string label="NumRefine" id="4">4</string>
 <string label="Method" id="5">1</string>
</xml>

