<?xml version="1.0" encoding="UTF-8"?>
<!--This file was created by G+Smo 21.12.0-->
<xml>
 <Matrix rows="5" cols="8" id="0">0.25 105 0.1645738487002657 3.229892442075876 67.96887588756582 0.006214505131390588 nan 460752 
0.125 253 0.03207284480516476 0.7345709508906488 22.85935778137254 0.009271288259059872 nan 921504 
0.0625 741 7.493880874114414e-05 0.003353200667033124 0.2437076580723882 0.0004087250491499454 nan 1843008 
0.03125 2485 2.361560151849196e-07 4.292968722932907e-05 0.008214344131408745 3.557259274374283e-06 -nan 3686016 
0.015625 9045 1.765859510248767e-08 1.167059820325694e-06 0.0004555009880602079 4.483497838463197e-08 0 7372032 
</Matrix>
 <string label="Label" id="1">Meshsize, dofs, l2err, h1err, h2err, iFaceErr, cond_num, (penalty)</string>
 <string label="Degree" id="2">5</string>
 <string label="Regularity" id="3">4</string>
 <string label="NumRefine" id="4">4</string>
 <string label="Method" id="5">1</string>
</xml>

