<?xml version="1.0" encoding="UTF-8"?>
<!--This file was created by G+Smo 21.12.0-->
<xml>
 <Matrix rows="5" cols="8" id="0">0.25 105 0.07834927842370887 1.753240936278025 44.72302181044602 3.160854442498799 nan 7.06968 
0.125 253 0.001282621625867648 0.05614302768373541 3.209731773222506 0.2382232741244016 -nan 14.13936 
0.0625 741 5.482854652168043e-06 0.000652994722359953 0.08649886949445094 0.002246263049964227 nan 28.27872 
0.03125 2485 5.604698054887176e-08 1.468109176410835e-05 0.004186437500566339 6.668022407612149e-05 -nan 56.55744 
0.015625 9045 7.432670423729446e-10 4.08758960700193e-07 0.0002351474439218179 1.017993946702643e-06 nan 113.11488 
</Matrix>
 <string label="Label" id="1">Meshsize, dofs, l2err, h1err, h2err, iFaceErr, cond_num, (penalty)</string>
 <string label="Degree" id="2">5</string>
 <string label="Regularity" id="3">4</string>
 <string label="NumRefine" id="4">4</string>
 <string label="Method" id="5">1</string>
</xml>

