<?xml version="1.0" encoding="UTF-8"?>
<!--This file was created by G+Smo 21.12.0-->
<xml>
 <Matrix rows="5" cols="8" id="0">0.25 78 0.2874477668673103 4.485974430267739 78.93363788324469 0.2556561940666976 -nan 87005.60000000001 
0.125 210 0.09591226186694038 1.807502364666781 37.29872230664018 0.04393098086366468 nan 174011.2 
0.0625 666 0.003296802191384732 0.08406145653728466 2.46892490418729 0.008118194017266003 nan 348022.4 
0.03125 2346 1.675419629881362e-05 0.0006140747114597536 0.06433695645217964 0.0004276488259904302 nan 696044.8 
0.015625 8778 1.087582076587455e-07 1.324025051183375e-05 0.006893458993707604 2.41311552034173e-05 nan 1392089.6 
</Matrix>
 <string label="Label" id="1">Meshsize, dofs, l2err, h1err, h2err, iFaceErr, cond_num, (penalty)</string>
 <string label="Degree" id="2">4</string>
 <string label="Regularity" id="3">3</string>
 <string label="NumRefine" id="4">4</string>
 <string label="Method" id="5">1</string>
</xml>

