<?xml version="1.0" encoding="UTF-8"?>
<!--This file was created by G+Smo 21.12.0-->
<xml>
 <Matrix rows="5" cols="8" id="0">0.25 78 0.108683985646564 2.272084469538167 56.04906822762526 3.50644609380748 -nan 16.96124 
0.125 210 0.004186358224370041 0.1604509042598574 9.246291237393277 0.7927079088883177 nan 33.92248 
0.0625 666 3.794574101380316e-05 0.004189387390318387 0.5739260375953153 0.01698515805849929 nan 67.84496 
0.03125 2346 7.439812775397825e-07 0.0002017306228298994 0.0592283443924567 0.0009458162991626575 nan 135.68992 
0.015625 8778 2.042577917873786e-08 1.167302620423526e-05 0.00697394078430094 5.862217268424479e-05 -nan 271.37984 
</Matrix>
 <string label="Label" id="1">Meshsize, dofs, l2err, h1err, h2err, iFaceErr, cond_num, (penalty)</string>
 <string label="Degree" id="2">4</string>
 <string label="Regularity" id="3">3</string>
 <string label="NumRefine" id="4">4</string>
 <string label="Method" id="5">1</string>
</xml>

