<?xml version="1.0" encoding="UTF-8"?>
<!--This file was created by G+Smo 21.12.0-->
<xml>
 <Matrix rows="5" cols="8" id="0">0.25 78 0.1031992307451887 2.167846616253614 53.02329709064611 2.294450921715128 nan 0.0438 
0.125 210 0.003628228447684539 0.1404199087473017 7.471200581496287 0.3725618615492017 -nan 0.0876 
0.0625 666 3.6363809117964e-05 0.004064625809152754 0.5508222525574481 0.01063788120698241 nan 0.1752 
0.03125 2346 7.245196483688796e-07 0.0001975311254182643 0.05759144548342109 0.0004773700700037526 -nan 0.3504 
0.015625 8778 2.01198321332256e-08 1.153262382074384e-05 0.006863220844846577 2.697762085443133e-05 -nan 0.7008 
</Matrix>
 <string label="Label" id="1">Meshsize, dofs, l2err, h1err, h2err, iFaceErr, cond_num, (penalty)</string>
 <string label="Degree" id="2">4</string>
 <string label="Regularity" id="3">3</string>
 <string label="NumRefine" id="4">4</string>
 <string label="Method" id="5">1</string>
</xml>

