<?xml version="1.0" encoding="UTF-8"?>
<!--This file was created by G+Smo 21.12.0-->
<xml>
 <Matrix rows="5" cols="8" id="0">0.25 105 0.08732989458199906 1.852648658778249 44.35207309903686 0.5177091712112227 nan 340.8104 
0.125 253 0.003374718113396562 0.1015086038632231 3.7145816128472 0.1089981631788539 nan 681.6208 
0.0625 741 6.488135894313348e-06 0.0006685059761659782 0.08569232001789969 0.001781818154056132 nan 1363.2416 
0.03125 2485 5.725434042190467e-08 1.457702215642539e-05 0.004062131549472546 3.553766033436033e-05 nan 2726.4832 
0.015625 9045 7.506561405978174e-10 4.092712919936906e-07 0.0002350516763226374 9.651958980883894e-07 nan 5452.9664 
</Matrix>
 <string label="Label" id="1">Meshsize, dofs, l2err, h1err, h2err, iFaceErr, cond_num, (penalty)</string>
 <string label="Degree" id="2">5</string>
 <string label="Regularity" id="3">4</string>
 <string label="NumRefine" id="4">4</string>
 <string label="Method" id="5">1</string>
</xml>

