<?xml version="1.0" encoding="UTF-8"?>
<!--This file was created by G+Smo 21.12.0-->
<xml>
 <Matrix rows="5" cols="8" id="0">0.25 105 0.2439692127801233 3.918778604567294 70.74349764309834 0.09535302364961041 nan 567488 
0.125 253 0.05346510972956413 1.153038611298985 27.59138162388615 0.01114562524810297 nan 1134976 
0.0625 741 0.0009645330921147049 0.02702046980973937 0.8896354153384596 0.001481448107388159 nan 2269952 
0.03125 2485 2.517951629959366e-06 0.000154876842835546 0.01312202238989031 3.417802773607287e-05 nan 4539904 
0.015625 9045 1.434983576913498e-08 1.765670052163956e-06 0.0003607063885922301 9.500986307124541e-07 nan 9079808 
</Matrix>
 <string label="Label" id="1">Meshsize, dofs, l2err, h1err, h2err, iFaceErr, cond_num, (penalty)</string>
 <string label="Degree" id="2">5</string>
 <string label="Regularity" id="3">4</string>
 <string label="NumRefine" id="4">4</string>
 <string label="Method" id="5">1</string>
</xml>

