<?xml version="1.0" encoding="UTF-8"?>
<!--This file was created by G+Smo 21.12.0-->
<xml>
 <Matrix rows="5" cols="8" id="0">0.25 78 0.1031977087227575 2.16782108361725 53.02280051541775 2.29428477484311 -nan 0.03272 
0.125 210 0.003627903694055489 0.1404152013388962 7.471133441991439 0.3725395064683047 nan 0.06544 
0.0625 666 3.636356119848587e-05 0.004064596550891702 0.5508172918545069 0.01063556123242555 nan 0.13088 
0.03125 2346 7.245193436414819e-07 0.0001975307651654642 0.05759131137818523 0.000477307674912704 nan 0.26176 
0.015625 8778 2.011982226048909e-08 1.153261515854202e-05 0.006863214352517358 2.697470359368787e-05 -nan 0.52352 
</Matrix>
 <string label="Label" id="1">Meshsize, dofs, l2err, h1err, h2err, iFaceErr, cond_num, (penalty)</string>
 <string label="Degree" id="2">4</string>
 <string label="Regularity" id="3">3</string>
 <string label="NumRefine" id="4">4</string>
 <string label="Method" id="5">1</string>
</xml>

