<?xml version="1.0" encoding="UTF-8"?>
<!--This file was created by G+Smo 21.12.0-->
<xml>
 <Matrix rows="5" cols="8" id="0">0.125 187 0.01323899428355308 0.4661418731923808 31.85406173880834 0.1252318617874133 -nan 2696.352 
0.0625 375 0.001546966155344195 0.06723340673724928 5.356201517514482 0.006286639467916123 -nan 5392.704 
0.03125 943 1.757840336419998e-05 0.001274431996137666 0.1664382822576383 3.463185516965735e-05 nan 10785.408 
0.015625 2847 1.289158216514133e-07 2.180360068456635e-05 0.004145994246507773 6.134287225108546e-07 nan 21570.816 
0.0078125 9727 1.911797032304972e-09 6.362034636057936e-07 0.0002469560814228743 1.759692896756762e-08 0 43141.632 
</Matrix>
 <string label="Label" id="1">Meshsize, dofs, l2err, h1err, h2err, iFaceErr, cond_num, (penalty)</string>
 <string label="Degree" id="2">5</string>
 <string label="Regularity" id="3">4</string>
 <string label="NumRefine" id="4">4</string>
 <string label="Method" id="5">1</string>
</xml>

