<?xml version="1.0" encoding="UTF-8"?>
<!--This file was created by G+Smo 21.12.0-->
<xml>
 <Matrix rows="5" cols="8" id="0">0.125 117 0.01637442764765559 0.6129287865763654 26.57552582186835 0.02609761465446779 -nan 160096 
0.0625 273 0.002213480639741303 0.1050526487938922 6.317118498616592 0.004952888178515216 nan 320192 
0.03125 777 7.478513376700778e-05 0.005711038028947565 0.5161942997625059 0.0001869417111490907 nan 640384 
0.015625 2553 1.264805764338165e-06 0.0002318837039968934 0.04759808563587731 1.043378524753185e-05 nan 1280768 
0.0078125 9177 3.379791772828541e-08 1.331043499378387e-05 0.005690199763716538 6.192353965954809e-07 0 2561536 
</Matrix>
 <string label="Label" id="1">Meshsize, dofs, l2err, h1err, h2err, iFaceErr, cond_num, (penalty)</string>
 <string label="Degree" id="2">4</string>
 <string label="Regularity" id="3">3</string>
 <string label="NumRefine" id="4">4</string>
 <string label="Method" id="5">1</string>
</xml>

