<?xml version="1.0" encoding="UTF-8"?>
<!--This file was created by G+Smo 21.12.0-->
<xml>
 <Matrix rows="5" cols="8" id="0">0.125 117 0.01456088295530381 0.5316668523131683 20.81249809882131 0.05823148554171244 nan 0.014 
0.0625 273 0.001921134317861242 0.0881450897448745 5.057956747059261 0.007660195716371213 -nan 0.028 
0.03125 777 6.045247671258476e-05 0.005008097892845334 0.4813709884971614 0.0002210467833984334 nan 0.056 
0.015625 2553 1.197368183649249e-06 0.0002278334776029465 0.04728003202196542 1.070610816400115e-05 -nan 0.112 
0.0078125 9177 3.364453041113955e-08 1.329153991957067e-05 0.005687102714026806 6.221940689506097e-07 0 0.224 
</Matrix>
 <string label="Label" id="1">Meshsize, dofs, l2err, h1err, h2err, iFaceErr, cond_num, (penalty)</string>
 <string label="Degree" id="2">4</string>
 <string label="Regularity" id="3">3</string>
 <string label="NumRefine" id="4">4</string>
 <string label="Method" id="5">1</string>
</xml>

