<?xml version="1.0" encoding="UTF-8"?>
<!--This file was created by G+Smo 21.12.0-->
<xml>
 <Matrix rows="5" cols="8" id="0">0.125 117 0.0145608904011548 0.531666954497654 20.8125144746984 0.05823299279086715 nan 0.06279999999999999 
0.0625 273 0.001921134722644272 0.08814509661223701 5.057957048797472 0.007660067622817457 -nan 0.1256 
0.03125 777 6.045247571027388e-05 0.005008097828773448 0.4813709881373378 0.0002210460890400904 nan 0.2512 
0.015625 2553 1.197368181559694e-06 0.0002278334773228864 0.04728003202079319 1.070609921043211e-05 nan 0.5024 
0.0078125 9177 3.364453036859798e-08 1.329153991877531e-05 0.0056871027140548 6.221940220081893e-07 0 1.0048 
</Matrix>
 <string label="Label" id="1">Meshsize, dofs, l2err, h1err, h2err, iFaceErr, cond_num, (penalty)</string>
 <string label="Degree" id="2">4</string>
 <string label="Regularity" id="3">3</string>
 <string label="NumRefine" id="4">4</string>
 <string label="Method" id="5">1</string>
</xml>

