<?xml version="1.0" encoding="UTF-8"?>
<!--This file was created by G+Smo 21.12.0-->
<xml>
 <Matrix rows="5" cols="8" id="0">0.125 187 0.01324095210146377 0.466168465885314 31.85163756514565 0.1253246819315969 nan 5.89344 
0.0625 375 0.001547115319632258 0.06723230358830252 5.355320763162794 0.006307265935115466 -nan 11.78688 
0.03125 943 1.757515103215489e-05 0.001274033813880234 0.166402735456669 3.646345585284132e-05 nan 23.57376 
0.015625 2847 1.289146258134098e-07 2.18023568080844e-05 0.004145300824049702 6.467556364591144e-07 nan 47.14752 
0.0078125 9727 1.91179292695975e-09 6.361946359244285e-07 0.0002469478146192639 1.802522569397237e-08 0 94.29504 
</Matrix>
 <string label="Label" id="1">Meshsize, dofs, l2err, h1err, h2err, iFaceErr, cond_num, (penalty)</string>
 <string label="Degree" id="2">5</string>
 <string label="Regularity" id="3">4</string>
 <string label="NumRefine" id="4">4</string>
 <string label="Method" id="5">1</string>
</xml>

