<?xml version="1.0" encoding="UTF-8"?>
<!--This file was created by G+Smo 21.12.0-->
<xml>
 <Matrix rows="5" cols="8" id="0">0.125 117 0.02004640449154462 0.7728113695003538 36.19806068225883 0.02508386394546708 -nan 1340840 
0.0625 273 0.003011834113876453 0.1494889080782977 9.953267756588468 0.004691710191360607 nan 2681680 
0.03125 777 0.0001933240118163684 0.01138293343299555 0.7910152491795031 0.0001715977622250464 nan 5363360 
0.015625 2553 2.383701594993606e-06 0.0002817560380857821 0.04994834833092741 1.033672161403092e-05 nan 10726720 
0.0078125 9177 3.699579045421008e-08 1.349538280706217e-05 0.005708316352378315 6.184184866261742e-07 0 21453440 
</Matrix>
 <string label="Label" id="1">Meshsize, dofs, l2err, h1err, h2err, iFaceErr, cond_num, (penalty)</string>
 <string label="Degree" id="2">4</string>
 <string label="Regularity" id="3">3</string>
 <string label="NumRefine" id="4">4</string>
 <string label="Method" id="5">1</string>
</xml>

