<?xml version="1.0" encoding="UTF-8"?>
<!--This file was created by G+Smo 21.12.0-->
<xml>
 <Matrix rows="5" cols="8" id="0">0.125 187 0.01455280019893381 0.5454196345608182 36.13613347753748 0.1250176615970126 nan 1134976 
0.0625 375 0.001640900108841804 0.07378051199493367 5.665628622634208 0.006212792103939748 -nan 2269952 
0.03125 943 2.452204691468777e-05 0.001709274170852544 0.1891294767988154 3.061554113737064e-05 nan 4539904 
0.015625 2847 1.517977608186754e-07 2.337635821965316e-05 0.004282108508511925 5.791375833567535e-07 nan 9079808 
0.0078125 9727 2.015412494775516e-09 6.444407243684738e-07 0.0002486075541931881 1.710198271080487e-08 0 18159616 
</Matrix>
 <string label="Label" id="1">Meshsize, dofs, l2err, h1err, h2err, iFaceErr, cond_num, (penalty)</string>
 <string label="Degree" id="2">5</string>
 <string label="Regularity" id="3">4</string>
 <string label="NumRefine" id="4">4</string>
 <string label="Method" id="5">1</string>
</xml>

