<?xml version="1.0" encoding="UTF-8"?>
<!--This file was created by G+Smo 21.12.0-->
<xml>
 <Matrix rows="5" cols="8" id="0">0.125 117 0.01456603392262325 0.5317502999881952 20.83142702785486 0.06142979160334884 -nan 32.53784 
0.0625 273 0.001921414271151937 0.08815120263694494 5.058562888866951 0.007704665567865044 nan 65.07568000000001 
0.03125 777 6.045187612077916e-05 0.00500806075867163 0.4813711707440828 0.0002206658892589321 nan 130.15136 
0.015625 2553 1.197367165073381e-06 0.0002278333344663016 0.04728007980507883 1.075476134976192e-05 -nan 260.30272 
0.0078125 9177 3.364453235281906e-08 1.329153975997033e-05 0.005687102895948435 6.223392905560246e-07 0 520.60544 
</Matrix>
 <string label="Label" id="1">Meshsize, dofs, l2err, h1err, h2err, iFaceErr, cond_num, (penalty)</string>
 <string label="Degree" id="2">4</string>
 <string label="Regularity" id="3">3</string>
 <string label="NumRefine" id="4">4</string>
 <string label="Method" id="5">1</string>
</xml>

