<?xml version="1.0" encoding="UTF-8"?>
<!--This file was created by G+Smo 21.12.0-->
<xml>
 <Matrix rows="5" cols="8" id="0">0.125 187 0.01323877552279084 0.4661413965342975 31.85451481573346 0.1252298802076021 nan 3320.984 
0.0625 375 0.001547003070878938 0.06723901684355388 5.356655670767902 0.006283633073483899 -nan 6641.968 
0.03125 943 1.75795658420273e-05 0.001274551450241614 0.1664470805505832 3.449412339249093e-05 nan 13283.936 
0.015625 2847 1.289180773882682e-07 2.180411620043855e-05 0.004146154894770474 6.116152557347625e-07 -nan 26567.872 
0.0078125 9727 1.911799146430164e-09 6.362068083960457e-07 0.0002469580713505258 1.757308741123316e-08 0 53135.744 
</Matrix>
 <string label="Label" id="1">Meshsize, dofs, l2err, h1err, h2err, iFaceErr, cond_num, (penalty)</string>
 <string label="Degree" id="2">5</string>
 <string label="Regularity" id="3">4</string>
 <string label="NumRefine" id="4">4</string>
 <string label="Method" id="5">1</string>
</xml>

