<?xml version="1.0" encoding="UTF-8"?>
<!--This file was created by G+Smo 21.12.0-->
<xml>
 <Matrix rows="5" cols="8" id="0">0.125 187 0.01324095486292394 0.4661685326993337 31.85164769645346 0.1253241243731681 -nan 4.22264 
0.0625 375 0.00154711570372718 0.06723232379183428 5.355321000335373 0.006307258810527215 nan 8.44528 
0.03125 943 1.757515346716641e-05 0.00127403397030487 0.1664027368946784 3.646622694310743e-05 nan 16.89056 
0.015625 2847 1.289146499624005e-07 2.180236015652734e-05 0.00414530083093584 6.468906026449734e-07 nan 33.78112 
0.0078125 9727 1.911793012351548e-09 6.361946527763949e-07 0.0002469478148147572 1.802717843348825e-08 0 67.56224 
</Matrix>
 <string label="Label" id="1">Meshsize, dofs, l2err, h1err, h2err, iFaceErr, cond_num, (penalty)</string>
 <string label="Degree" id="2">5</string>
 <string label="Regularity" id="3">4</string>
 <string label="NumRefine" id="4">4</string>
 <string label="Method" id="5">1</string>
</xml>

